{
  // "clangd.semanticHighlighting": true,
  "clangd.arguments": [
    "--background-index",
    "-pretty",
    "--clang-tidy"
  ],
  // "languageserver": {
  //   "golang": {
  //     "command": "gopls",
  //     "rootPatterns": [
  //       "go.mod"
  //     ],
  //     "filetypes": [
  //       "go"
  //     ],
  //   }
  // },
  "go.goplsOptions": {
      "directoryFilters": ["-mocks"]
  },
  // "python.jediEnabled": false,
  "yaml.format.enable": true,
  "pyright.inlayHints.functionReturnTypes": false,
  "pyright.inlayHints.variableTypes": false,
  "pyright.inlayHints.parameterTypes": false,
  "clangd.path": "~/.config/coc/extensions/coc-clangd-data/install/13.0.0/clangd_13.0.0/bin/clangd"
}
